coinalyze/__init__.py
coinalyze/__version__.py
coinalyze/client.py
coinalyze/constants.py
coinalyze/enums.py
coinalyze/py.typed
coinalyze/types.py
coinalyze/util/__init__.py
coinalyze/util/base.py
coinalyze/util/pandas.py
coinalyze-0.1.1.dist-info/METADATA
coinalyze-0.1.1.dist-info/WHEEL
coinalyze-0.1.1.dist-info/licenses/LICENSE
coinalyze-0.1.1.dist-info/RECORD
