Metadata-Version: 2.4
Name: coinalyze
Version: 0.1.1
Summary: Unofficial Python client for coinalyze.net REST API
Project-URL: Homepage, https://github.com/ivarurdalen/coinalyze
Project-URL: Source, https://github.com/ivarurdalen/coinalyze
Project-URL: Changelog, https://github.com/ivarurdalen/coinalyze/blob/main/CHANGELOG.md
Author-email: Ivar Soares Urdalen <ivar.urdalen@gmail.com>
License-Expression: MIT
License-File: LICENSE
Classifier: Intended Audience :: Developers
Classifier: License :: OSI Approved :: MIT License
Classifier: Programming Language :: Python :: 3 :: Only
Classifier: Programming Language :: Python :: 3.11
Classifier: Programming Language :: Python :: 3.12
Classifier: Programming Language :: Python :: 3.13
Classifier: Topic :: Software Development :: Libraries :: Python Modules
Requires-Python: >=3.11
Requires-Dist: httpx
Requires-Dist: httpx-retries
Requires-Dist: pyrate-limiter
Provides-Extra: pandas
Requires-Dist: pandas; extra == 'pandas'
